Trees/AVLTree.py
Trees/BST.py
Trees/BinaryTree.py
Trees/Heap.py
cs4_tree_datastructure-1.0.0.dist-info/DESCRIPTION.rst
cs4_tree_datastructure-1.0.0.dist-info/METADATA
cs4_tree_datastructure-1.0.0.dist-info/RECORD
cs4_tree_datastructure-1.0.0.dist-info/WHEEL
cs4_tree_datastructure-1.0.0.dist-info/metadata.json
cs4_tree_datastructure-1.0.0.dist-info/top_level.txt
