Metadata-Version: 2.0
Name: cs4-tree-datastructure
Version: 1.0.0
Summary: Implemenation of BST, AVL and Heap
Home-page: https://github.com/rayegleekel/trees
Author: Raye Gleekel
License: MIT
Platform: UNKNOWN
Classifier: License :: OSI Approved :: MIT License
Classifier: Programming Language :: Python :: 3
Classifier: Programming Language :: Python :: 3.7
